openrewrite_python_test_recipes/python_test_recipe.py
openrewrite_python_test_recipes-0.3.0.dist-info/METADATA
openrewrite_python_test_recipes-0.3.0.dist-info/WHEEL
openrewrite_python_test_recipes-0.3.0.dist-info/top_level.txt
openrewrite_python_test_recipes-0.3.0.dist-info/RECORD
