Metadata-Version: 2.2
Name: openrewrite-python-test-recipes
Version: 0.3.0
Summary: Testing recipe introspection
Requires-Python: >=3.9
Requires-Dist: openrewrite>=1.30.0
Provides-Extra: dev
Requires-Dist: poethepoet==0.31.1; extra == "dev"
